<?xml version="1.0" encoding="ISO-8859-1"?>
<RECIPES>
    <RECIPE>
        <NAME>xBmt&#45;&#50;&#48;&#50;&#48;&#48;&#55;&#51;&#48;&#32;Warm&#32;Pressure&#32;Fermented&#32;Lager</NAME>
        <VERSION>1</VERSION>
        <TYPE>Extract</TYPE>
        <NOTES>http&#58;&#47;&#47;brulosophy&#46;com&#47;&#50;&#48;&#50;&#48;&#47;&#48;&#55;&#47;&#51;&#48;&#47;examining&#45;the&#45;qualitative&#45;and&#45;quantitative&#45;impact&#45;of&#45;fermenting&#45;pale&#45;lager&#45;under&#45;pressure&#45;at&#45;ale&#45;temperature&#45;the&#45;bru&#45;club&#45;xbmt&#45;series&#47;</NOTES>
        <STYLE>
            <NAME>American&#32;Amber&#32;Ale</NAME>
            <CATEGORY>American&#32;Pale&#32;Ale</CATEGORY>
            <VERSION>1</VERSION>
            <CATEGORY_NUMBER>6</CATEGORY_NUMBER>
            <STYLE_LETTER>B</STYLE_LETTER>
            <STYLE_GUIDE>BJCP&#32;&#49;&#57;&#57;&#57;</STYLE_GUIDE>
            <TYPE>Ale</TYPE>
            <OG_MIN>1.045</OG_MIN>
            <OG_MAX>1.056</OG_MAX>
            <FG_MIN>1.01</FG_MIN>
            <FG_MAX>1.015</FG_MAX>
            <IBU_MIN>20</IBU_MIN>
            <IBU_MAX>40</IBU_MAX>
            <COLOR_MIN>11</COLOR_MIN>
            <COLOR_MAX>18</COLOR_MAX>
        </STYLE>
        <BREWER>Mike&#32;Olivier&#32;and&#32;Josh&#32;Sharp</BREWER>
        <BATCH_SIZE>5.6</BATCH_SIZE>
        <BOIL_SIZE>8.21</BOIL_SIZE>
        <BOIL_TIME>75</BOIL_TIME>
        <EFFICIENCY>71.8</EFFICIENCY>
        <OG>1.048</OG>
        <FG>1.014</FG>
        <ABV>4.46 %</ABV>
        <EST_ABV>4.46 %</EST_ABV>
        <IBU>22.7</IBU>
        <EST_OG>1.048 SG</EST_OG>
        <EST_FG>1.014 SG</EST_FG>
        <EST_COLOR>3.5 SRM</EST_COLOR>
        <CARBONATION>2.3</CARBONATION>
        <HOPS>
            <HOP>
                <BF_ID>new-C5co8NRiQiTMUroCim8leS5yxsSwv7</BF_ID>
                <NAME>Saaz</NAME>
                <VERSION>1</VERSION>
                <ALPHA>4</ALPHA>
                <AMOUNT>0.0094</AMOUNT>
                <USE>Boil</USE>
                <TIME>75</TIME>
                <FORM>Pellet</FORM>
                <TEMPERATURE>NaN</TEMPERATURE>
                <HOP_TEMP>NaN</HOP_TEMP>
            </HOP>
            <HOP>
                <BF_ID>new-C5co8NRiQiTMUroCim8leS5yxsSwv7</BF_ID>
                <NAME>Saaz</NAME>
                <VERSION>1</VERSION>
                <ALPHA>4</ALPHA>
                <AMOUNT>0.0038</AMOUNT>
                <USE>Boil</USE>
                <TIME>10</TIME>
                <FORM>Pellet</FORM>
                <TEMPERATURE>NaN</TEMPERATURE>
                <HOP_TEMP>NaN</HOP_TEMP>
            </HOP>
            <HOP>
                <BF_ID>new-C5co8NRiQiTMUroCim8leS5yxsSwv7</BF_ID>
                <NAME>Saaz</NAME>
                <VERSION>1</VERSION>
                <ALPHA>4</ALPHA>
                <AMOUNT>0.0038</AMOUNT>
                <USE>Boil</USE>
                <TIME>0</TIME>
                <FORM>Pellet</FORM>
                <TEMPERATURE>NaN</TEMPERATURE>
                <HOP_TEMP>NaN</HOP_TEMP>
            </HOP>
        </HOPS>
        <FERMENTABLES>
            <FERMENTABLE>
                <BF_ID>new-kmBYja4cMclZhY35JkmdVYd0EO3pej</BF_ID>
                <NAME>Pilsner&#32;Dry&#32;Extract</NAME>
                <SUPPLIER/>
                <ORIGIN>US</ORIGIN>
                <VERSION>1</VERSION>
                <TYPE>Dry&#32;Extract</TYPE>
                <AMOUNT>0.78</AMOUNT>
                <YIELD>91.3043478</YIELD>
                <COLOR>3</COLOR>
                <ADD_AFTER_BOIL>FALSE</ADD_AFTER_BOIL>
                <NOT_FERMENTABLE>false</NOT_FERMENTABLE>
                <IBU_GAL_PER_LB>NaN</IBU_GAL_PER_LB>
            </FERMENTABLE>
        </FERMENTABLES>
        <YEASTS>
            <YEAST>
                <BF_ID>new-uhARuDPuxMJzfL8D5mL9Ms4ckVM2Jo</BF_ID>
                <NAME>Bohemian&#32;Lager</NAME>
                <VERSION>1</VERSION>
                <TYPE>Lager</TYPE>
                <FORM>Liquid</FORM>
                <AMOUNT>1</AMOUNT>
                <LABORATORY>Wyeast&#32;Labs</LABORATORY>
                <PRODUCT_ID>2124</PRODUCT_ID>
                <DISPLAY_AMOUNT>1 pkg</DISPLAY_AMOUNT>
                <ATTENUATION>71</ATTENUATION>
                <MIN_TEMPERATURE/>
                <MAX_TEMPERATURE/>
            </YEAST>
        </YEASTS>
        <MASH>
            <BF_ID/>
            <NAME>Single&#32;Infusion&#44;&#32;Light&#32;Body&#44;&#32;No&#32;Mash&#32;Out</NAME>
            <VERSION>1</VERSION>
            <GRAIN_TEMP>20</GRAIN_TEMP>
            <MASH_STEPS>
                <MASH_STEP>
                    <NAME>Mash&#32;In</NAME>
                    <VERSION>1</VERSION>
                    <TYPE>Infusion</TYPE>
                    <STEP_TEMP>65.6</STEP_TEMP>
                    <STEP_TIME>75</STEP_TIME>
                </MASH_STEP>
            </MASH_STEPS>
        </MASH>
        <EQUIPMENT>
            <NAME>&#48;&#49;&#32;Brouwpunt&#32;&#53;L&#32;&#40;&#55;&#53;min&#41;&#32;&#40;rev&#32;&#52;&#41;</NAME>
            <VERSION>1</VERSION>
            <BOIL_SIZE>8.21</BOIL_SIZE>
            <BATCH_SIZE>5.6</BATCH_SIZE>
            <TRUB_CHILLER_LOSS>0.12</TRUB_CHILLER_LOSS>
            <LAUTER_DEADSPACE>0</LAUTER_DEADSPACE>
            <BOIL_TIME>75</BOIL_TIME>
            <HOP_UTILIZATION>100</HOP_UTILIZATION>
            <EVAP_RATE>21.924482338611448</EVAP_RATE>
            <CALC_BOIL_VOLUME>true</CALC_BOIL_VOLUME>
        </EQUIPMENT>
        <BF_FERMENTATION_PROFILE_ID/>
        <BF_FERMENTATION_PROFILE_NAME>Imported</BF_FERMENTATION_PROFILE_NAME>
        <FERMENTATION_STAGES>3</FERMENTATION_STAGES>
        <PRIMARY_AGE>4</PRIMARY_AGE>
        <PRIMARY_TEMP>19.4</PRIMARY_TEMP>
        <SECONDARY_AGE>10</SECONDARY_AGE>
        <SECONDARY_TEMP>19.4</SECONDARY_TEMP>
        <TERTIARY_AGE>30</TERTIARY_AGE>
        <TERTIARY_TEMP>18.3</TERTIARY_TEMP>
    </RECIPE>
</RECIPES>